{"blog_2024-10-20-introducing-textwire-a-domain-specific-language-for-go_index.md":"YvCJmFu9","blog_2024-10-24-textwire-v2.1.0-release-notes.md":"8GTP3t5w","blog_2025-01-10-textwire-v2.4.0.md":"CDRN100S","blog_2026-02-05-textwire-v3.md":"CFGLUNsZ","blog_index.md":"BZgNP4tK","community.md":"Dc_Bz-vS","index.md":"zImirhA6","v1_faq.md":"Dzs66YpP","v1_functions_arr.md":"BdocUX0Q","v1_functions_float.md":"rsLx2yWL","v1_functions_guide.md":"DKSDKGe9","v1_functions_int.md":"E58XSJR1","v1_functions_str.md":"DNlT41oB","v1_get-started_eval-file.md":"BWjykJAt","v1_get-started_eval-string.md":"BmrL02ct","v1_get-started_get-started.md":"DoB1Muis","v1_index.md":"B_PvG_t8","v1_language-elements_expressions.md":"wiFe_UPU","v1_language-elements_literals.md":"DNn_3J7v","v1_language-elements_other.md":"MtHvHwLf","v1_language-elements_statements.md":"BLzC3ZSE","v1_language-elements_syntax.md":"tLg2M_jh","v2_faq_questions.md":"Dfzp-lli","v2_faq_usage.md":"-C9fw5EW","v2_functions_arr.md":"ChQMpWBY","v2_functions_bool.md":"Dy-jN5SX","v2_functions_float.md":"DfscHpD8","v2_functions_guide.md":"D3C5taTg","v2_functions_int.md":"BNmQ4pIZ","v2_functions_str.md":"Bg4ztAvu","v2_get-started.md":"DngOOqiS","v2_guides_configurations.md":"BIYcBsWp","v2_guides_custom-functions.md":"C6O7bRr2","v2_guides_error-handling.md":"Bnj-HyPa","v2_guides_eval-file.md":"Dp5dbnnM","v2_guides_eval-string.md":"I0ambBZN","v2_guides_loops.md":"ClLDMKVh","v2_guides_template-usage.md":"B_QpbUhH","v2_index.md":"DD-PHxb4","v2_language-elements_expressions.md":"B00-BtRY","v2_language-elements_literals.md":"D53FesQJ","v2_language-elements_other.md":"8zhBAIs0","v2_language-elements_statements.md":"C4141Dsh","v2_language-elements_syntax.md":"DcI9JQy1","v2_upgrade.md":"BnbpIGJ2","v3_faq.md":"rVqwcpJy","v3_functions_arr.md":"jhe1X4NC","v3_functions_bool.md":"BXcTMVFp","v3_functions_float.md":"B_imAxtW","v3_functions_global.md":"BP9umgWs","v3_functions_guide.md":"C4uYJmSF","v3_functions_int.md":"BSEdgUIW","v3_functions_str.md":"CxC7AJ1u","v3_get-started.md":"fdUAzqYF","v3_guides_configurations.md":"BY9KJB04","v3_guides_custom-functions.md":"rjt3w1ib","v3_guides_error-handling.md":"qAJPXUR2","v3_guides_eval-file.md":"BOUl1BVe","v3_guides_eval-string.md":"DMb0z4Fg","v3_guides_loops.md":"DlFm32B5","v3_guides_template-embedding.md":"wU1XVQRQ","v3_guides_template-usage.md":"CE5nkuBM","v3_index.md":"C6mmi52j","v3_language-elements_directives.md":"BPJgedcK","v3_language-elements_expressions.md":"ByRJYXny","v3_language-elements_literals.md":"74Ut61My","v3_language-elements_other.md":"DQ2YE_HK","v3_language-elements_syntax.md":"CiaUjpHu","v3_upgrade.md":"H2YrTsJW"}
